gtop_sprokkel78/CHANGELOG.txt
gtop_sprokkel78/LICENSE
gtop_sprokkel78/README.md
gtop_sprokkel78/__init__.py
gtop_sprokkel78/gtop.css
gtop_sprokkel78/gtop.py
gtop_sprokkel78/gtop.svg
gtop_sprokkel78/images/b_applications.png
gtop_sprokkel78/images/b_connections.png
gtop_sprokkel78/images/b_menu.png
gtop_sprokkel78/images/b_network.png
gtop_sprokkel78/images/b_pause.png
gtop_sprokkel78/images/b_play.png
gtop_sprokkel78/images/b_services.png
gtop_sprokkel78/images/b_system.png
gtop_sprokkel78/images/b_traffic.png
gtop_sprokkel78/images/b_users.png
gtop_sprokkel78-1.2.0.dist-info/METADATA
gtop_sprokkel78-1.2.0.dist-info/WHEEL
gtop_sprokkel78-1.2.0.dist-info/licenses/LICENSE
gtop_sprokkel78-1.2.0.dist-info/RECORD
